stdLogger/__init__.py
stdLogger/std_logs.py
std_logger-0.1.6.dist-info/METADATA
std_logger-0.1.6.dist-info/WHEEL
std_logger-0.1.6.dist-info/top_level.txt
std_logger-0.1.6.dist-info/RECORD
