Metadata-Version: 2.1
Name: std-logger
Version: 0.1.6
Summary: logs tools
Home-page: UNKNOWN
Author: wei.fu
Author-email: mefuwei@163.com
License: UNKNOWN
Platform: UNKNOWN
Classifier: Programming Language :: Python :: 3
Classifier: License :: OSI Approved :: MIT License
Classifier: Operating System :: OS Independent
Requires-Dist: loguru
Requires-Dist: Flask-Log-Request-ID
